kathurimasample-0.0.1.dist-info/DESCRIPTION.rst
kathurimasample-0.0.1.dist-info/METADATA
kathurimasample-0.0.1.dist-info/RECORD
kathurimasample-0.0.1.dist-info/WHEEL
kathurimasample-0.0.1.dist-info/entry_points.txt
kathurimasample-0.0.1.dist-info/metadata.json
kathurimasample-0.0.1.dist-info/top_level.txt
myfibo/fibo.py
