Metadata-Version: 2.0
Name: kathurimasample
Version: 0.0.1
Summary: Kathurima sample package Python project
Home-page: https://github.com/KathurimaKimathi/pythonproject
Author: Kathurima Kimathi
Author-email: kathurimakimathi@gmail.com
License: MIT
Platform: UNKNOWN
Classifier: License :: OSI Approved :: MIT License
Classifier: Programming Language :: Python :: 3
Classifier: Programming Language :: Python :: 3.7
Requires-Dist: requests
